messgeraet_anzapfen/__init__.py
messgeraet_anzapfen/anzapfen.ini
messgeraet_anzapfen/configurable.py
messgeraet_anzapfen/constant.ini
messgeraet_anzapfen/econsens3.ini
messgeraet_anzapfen/econsens3.py
messgeraet_anzapfen/gpio.py
messgeraet_anzapfen/main.py
messgeraet_anzapfen/sensor.py
messgeraet_anzapfen/serial.py
messgeraet_anzapfen/server.py
messgeraet_anzapfen/server_token.py
messgeraet_anzapfen/statusled.py
messgeraet_anzapfen/token.ini
messgeraet_anzapfen/verify.py
messgeraet_anzapfen/sensors/__init__.py
messgeraet_anzapfen/sensors/constant.py
messgeraet_anzapfen/sensors/econsens3.py
messgeraet_anzapfen/sensors/sensor.py
messgeraet_anzapfen-0.5.2.dist-info/DESCRIPTION.rst
messgeraet_anzapfen-0.5.2.dist-info/METADATA
messgeraet_anzapfen-0.5.2.dist-info/RECORD
messgeraet_anzapfen-0.5.2.dist-info/WHEEL
messgeraet_anzapfen-0.5.2.dist-info/entry_points.txt
messgeraet_anzapfen-0.5.2.dist-info/metadata.json
messgeraet_anzapfen-0.5.2.dist-info/top_level.txt
