Metadata-Version: 2.0
Name: messgeraet-anzapfen
Version: 0.5.2
Summary: Anzapfen von Messgeräten und senden der Werte an einen Server
Home-page: https://gitlab.com/messgeraet/anzapfen
Author: Sebastian Stigler
Author-email: sebastian@sebastian-stigler.de
License: mit
Platform: UNKNOWN
Classifier: Development Status :: 4 - Beta
Classifier: License :: OSI Approved :: MIT License
Classifier: Operating System :: POSIX
Classifier: Operating System :: POSIX :: Linux
Classifier: Programming Language :: Python
Classifier: Programming Language :: Python :: 3
Classifier: Programming Language :: Python :: 3.5
Classifier: Programming Language :: Python :: 3.6
Requires-Dist: certifi (==2017.4.17)
Requires-Dist: chardet (==3.0.4)
Requires-Dist: coloredlogs (==7.1)
Requires-Dist: humanfriendly (==4.4)
Requires-Dist: idna (==2.5)
Requires-Dist: PyJWT (==1.5.2)
Requires-Dist: requests (==2.18.1)
Requires-Dist: urllib3 (==1.21.1)
Requires-Dist: colorama (==0.3.9)
